handwriting_recognizer/__init__.py
handwriting_recognizer/main.py
handwriting_recognizer-0.1.2.dist-info/entry_points.txt
handwriting_recognizer-0.1.2.dist-info/METADATA
handwriting_recognizer-0.1.2.dist-info/WHEEL
handwriting_recognizer-0.1.2.dist-info/RECORD
