Metadata-Version: 2.1
Name: handwriting-recognizer
Version: 0.1.2
Summary: handwriting project recognizer using paint
Author: Aditya Unnikrishnan
Author-email: adiunni@hotmail.com
Requires-Python: >=3.7,<4.0
Classifier: Programming Language :: Python :: 3
Classifier: Programming Language :: Python :: 3.7
Classifier: Programming Language :: Python :: 3.8
Classifier: Programming Language :: Python :: 3.9
Classifier: Programming Language :: Python :: 3.10
Classifier: Programming Language :: Python :: 3.11
Requires-Dist: opencv-python (>=4.7.0.72,<5.0.0.0)
Requires-Dist: pillow (>=9.5.0,<10.0.0)
Requires-Dist: pyscreenshot (>=3.1,<4.0)
Requires-Dist: scikit-learn (>=1.2.2,<2.0.0)
Requires-Dist: tk (>=0.1.0,<0.2.0)
